disnakedb/__init__.py
disnakedb/aioinit.py
disnakedb/init.py
disnakedb-0.1.3.dist-info/WHEEL
disnakedb-0.1.3.dist-info/METADATA
disnakedb-0.1.3.dist-info/RECORD
